{"coord": {"lon": 20.9579, "lat": 52.3314}, "weather": [{"id": 741, "main": "Fog", "description": "fog", "icon": "50d"}], "base": "stations", "main": {"temp": 15.86, "feels_like": 15.96, "temp_min": 13.13, "temp_max": 17.43, "pressure": 1017, "humidity": 94, "sea_level": 1017, "grnd_level": 1007}, "visibility": 250, "wind": {"speed": 2.06, "deg": 150}, "clouds": {"all": 75}, "dt": 1756962096, "sys": {"type": 2, "id": 2000992, "country": "PL", "sunrise": 1756957951, "sunset": 1757006300}, "timezone": 7200, "id": 7533497, "name": "Gmina \u0141omianki", "cod": 200}